GuasKD/__init__.py
GuasKD/__main__.py
GuasKD/kdtree.py
guaskdtreefiltering-0.1.1.dist-info/licenses/LICENSE
guaskdtreefiltering-0.1.1.dist-info/METADATA
guaskdtreefiltering-0.1.1.dist-info/WHEEL
guaskdtreefiltering-0.1.1.dist-info/top_level.txt
guaskdtreefiltering-0.1.1.dist-info/RECORD
