Metadata-Version: 2.4
Name: GuasKDTreeFiltering
Version: 0.1.1
Summary: Spatial and Bilateral filtering using Gaussian KDTree data structures
Author-email: Manideepu Reddy Enugala <enugalamanideepreddy99@gmail.com>
License: MIT License
Project-URL: Homepage, https://github.com/enugalamanideepreddy/GuassianKDTreeFiltering
Project-URL: Issues, https://github.com/enugalamanideepreddy/GuassianKDTreeFiltering/issues
Classifier: Programming Language :: Python :: 3
Classifier: License :: OSI Approved :: MIT License
Classifier: Operating System :: OS Independent
Requires-Python: >=3.9
License-File: LICENSE
Requires-Dist: numpy
Requires-Dist: tqdm
Dynamic: license-file
